zeppy/__init__.py
zeppy/eppyREPserver.py
zeppy/eppyREQclient.py
zeppy/ppipes.py
zeppy/ptcp.py
zeppy/runIDFs.py
zeppy/z_runners.py
zeppy/zeppy.py
zeppy-0.1.4.dist-info/AUTHORS.rst
zeppy-0.1.4.dist-info/LICENSE
zeppy-0.1.4.dist-info/METADATA
zeppy-0.1.4.dist-info/WHEEL
zeppy-0.1.4.dist-info/top_level.txt
zeppy-0.1.4.dist-info/RECORD
