Metadata-Version: 2.1
Name: zeppy
Version: 0.1.4
Summary: distributed processing for eppy
Home-page: https://github.com/santoshphilip/zeppy
Author: Santosh Philip
Author-email: Santosh@example.com
Keywords: zeppy
Classifier: Development Status :: 2 - Pre-Alpha
Classifier: Intended Audience :: Developers
Classifier: Natural Language :: English
Classifier: Programming Language :: Python :: 3
Classifier: Programming Language :: Python :: 3.5
Classifier: Programming Language :: Python :: 3.6
Classifier: Programming Language :: Python :: 3.7
Classifier: Programming Language :: Python :: 3.8
Requires-Python: >=3.5
License-File: LICENSE
License-File: AUTHORS.rst
